{
  "Abholung Personalausweis": "1549",
  "Abholung Reisepass": "1550",
  "Abmeldung Nebenwohnsitz": "1554",
  "Abmeldung Wohnsitz ins Ausland": "1555",
  "Anmeldung - Zuzug aus dem Ausland": "1570",
  "Anmeldung - Zuzug aus dem Bundesgebiet": "1552",
  "Beantragung Personalausweis": "1545",
  "Beantragung Reisepass": "1547",
  "Beantragung vorläufiger Personalausweis": "1546",
  "Beantragung vorläufiger Reisepass": "1548",
  "Beglaubigung": "1556",
  "Elektronische ID-Karte für Bürger*Innen der EU": "1569",
  "Fischereischein": "1583",
  "Führerscheinumtausch": "1557",
  "Führungszeugnis": "1558",
  "Gewerbezentralregisterauszug": "1559",
  "Kircheneintritt / -austritt": "1560",
  "Melde- / Lebensbescheinigung": "1562",
  "Melderegisterauskunft (einfach / erweitert)": "1578",
  "Moers-Pass": "1564",
  "PIN für Personalausweis": "1568",
  "Prüfung ausländischer Urkunden": "1571",
  "Schwerbehindertenangelegenheiten": "1563",
  "Steuer-ID": "1565",
  "Ummeldung Wohnsitz innerhalb von Moers": "1553",
  "Untersuchungsberechtigungsschein": "1566",
  "Verlustmeldung Ausweis- oder Passdokument": "1551",
  "Wiedererteilung Führerschein": "1567"
}
